MANIFEST.in
README.txt
setup.py
metanl/__init__.py
metanl/download.py
metanl/english.py
metanl/extprocess.py
metanl/freeling.py
metanl/general.py
metanl/japanese.py
metanl/leeds_corpus_reader.py
metanl/snowball.py
metanl/test_unicode.py
metanl/todo.txt
metanl/wordlist.py
metanl.egg-info/PKG-INFO
metanl.egg-info/SOURCES.txt
metanl.egg-info/dependency_links.txt
metanl.egg-info/requires.txt
metanl.egg-info/top_level.txt
metanl/data/freeling/cy.cfg
metanl/data/freeling/en.cfg
metanl/data/freeling/es.cfg
metanl/data/freeling/generic_splitter.dat
metanl/data/freeling/ident.cfg
metanl/data/freeling/it.cfg
metanl/data/freeling/pt.cfg
metanl/data/freeling/ru.cfg
metanl/data/wordlists/google-unigrams.txt
metanl/data/wordlists/leeds-internet-ar.txt
metanl/data/wordlists/leeds-internet-de.txt
metanl/data/wordlists/leeds-internet-es.txt
metanl/data/wordlists/leeds-internet-fr.txt
metanl/data/wordlists/leeds-internet-it.txt
metanl/data/wordlists/leeds-internet-ja.txt
metanl/data/wordlists/leeds-internet-pt.txt
metanl/data/wordlists/leeds-internet-ru.txt
metanl/data/wordlists/leeds-internet-zh.txt
metanl/data/wordlists/multi-en.txt
metanl/data/wordlists/multilingual.txt
metanl/data/wordlists/twitter-orig.txt
metanl/data/wordlists/twitter.txt