Metadata-Version: 1.1
Name: metanl
Version: 0.5.5
Summary: Multilingual natural language tools, wrapping NLTK and other systems.
Home-page: http://github.com/commonsense/metanl/
Author: MIT Media Lab, Digital Intuition group
Author-email: conceptnet@media.mit.edu
License: MIT
Platform: any
Classifier: Intended Audience :: Developers
Classifier: Intended Audience :: Science/Research
Classifier: License :: OSI Approved :: MIT License
Classifier: Natural Language :: English
Classifier: Operating System :: MacOS
Classifier: Operating System :: Microsoft :: Windows
Classifier: Operating System :: POSIX
Classifier: Operating System :: Unix
Classifier: Programming Language :: C
Classifier: Programming Language :: Python :: 2.5
Classifier: Programming Language :: Python :: 2.6
Classifier: Programming Language :: Python :: 2.7
Classifier: Topic :: Scientific/Engineering
Classifier: Topic :: Software Development
Classifier: Topic :: Text Processing :: Linguistic
